spark_quality_rules_tools/__init__.py
spark_quality_rules_tools/functions/__init__.py
spark_quality_rules_tools/functions/generator.py
spark_quality_rules_tools/utils/__init__.py
spark_quality_rules_tools/utils/color.py
spark_quality_rules_tools/utils/resolve.py
spark_quality_rules_tools/utils/rules.py
spark_quality_rules_tools/utils/resource/resolve_edge.conf
spark_quality_rules_tools/utils/resource/resolve_sandbox.conf
spark_quality_rules_tools/utils/resource/rules.json
spark_quality_rules_tools-0.9.11.dist-info/LICENSE
spark_quality_rules_tools-0.9.11.dist-info/METADATA
spark_quality_rules_tools-0.9.11.dist-info/WHEEL
spark_quality_rules_tools-0.9.11.dist-info/top_level.txt
spark_quality_rules_tools-0.9.11.dist-info/RECORD
