Metadata-Version: 2.1
Name: spark-quality-rules-tools
Version: 0.9.11
Summary: spark_quality_rules_tools
Home-page: https://github.com/jonaqp/spark_quality_rules_tools/
Author: Jonathan Quiza
Author-email: jony327@gmail.com
License: UNKNOWN
Download-URL: https://github.com/jonaqp/spark_quality_rules_tools/archive/main.zip
Keywords: spark,dq,rules,hammurabies
Platform: UNKNOWN
Classifier: Development Status :: 5 - Production/Stable
Classifier: Intended Audience :: Developers
Classifier: Intended Audience :: Science/Research
Classifier: Topic :: Scientific/Engineering :: Artificial Intelligence
Classifier: License :: OSI Approved :: Apache Software License
Classifier: Programming Language :: Python :: 3.9
License-File: LICENSE
Requires-Dist: pandas (==2.0.1)
Requires-Dist: numpy (==1.24.3)
Requires-Dist: findspark (==2.0.1)
Requires-Dist: pyspark (==3.1.1)
Requires-Dist: pyarrow (==12.0.0)
Requires-Dist: setuptools (==58.2.0)
Requires-Dist: wheel (==0.40.0)
Requires-Dist: spark-dataframe-tools (>=0.4.0)
Requires-Dist: color-tools (>=0.0.2)
Requires-Dist: pyhocon (==0.3.60)
Requires-Dist: tqdm (==4.65.0)
Requires-Dist: prettytable (==3.8.0)
